{
    "sheet": [
        {
            "number": "1",
            "image": "motrin_instagram_fr.png",
            "alt": "Icône Motrin Instagram",
            "path": "/"
        },
        {
            "number": "2",
            "image": "motrin_fb_fr.png",
            "alt": "Icône Motrin FaceBook",
            "path": "/"
        },
        {
            "number": "3",
            "image": "motrin_youtube_fr.png",
            "alt": "Icône Motrin YouTube",
            "path": "/"
        },
        {
            "number": "4",
            "image": "motrin-treatingbackpain-frheader-min.jpg",
            "alt": "Dame souffrant de mal de dos",
            "path": "/symptomes-chez-les-adultes/mal-de-dos/traitement-de-la-douleur-au-haut-du-dos-bas-du-dos"
        },
        {
            "number": "5",
            "image": "teething-taco-4.png",
            "alt": "Suspension MOTRIN® Nourrissons Douleur et fièvre, 8 heures, Petits fruits, Sans colorant, 120 ml",
            "path": "/symptomes-chez-les-nourrissons-et-les-enfants/traiter-le-mal-de-dents-et-la-douleur-de-la-dentition"
        },
        {
            "number": "6",
            "image": "fr_mot_platinum-1.png",
            "alt": "Motrin Platine Muscles et corps, 40 caplets",
            "path": "/symptomes-chez-les-adultes/mal-de-dos/causes-de-la-douleur-au-haut-et-au-bas-du-dos"
        },
        {
            "number": "7",
            "image": "motrin-fr-ktd-childrens-header.jpg",
            "alt": "Produits Tylenol et Motrin pour nourrissons contre la fièvre et la douleur",
            "path": "/symptomes-chez-les-nourrissons-et-les-enfants/faire-la-difference-page-d-accueil/faire-la-difference"
        },
        {
            "number": "8",
            "image": "motrin-fr-infantchildsymptomslanding-callout_1.jpg",
            "alt": "Produits Tylenol et Motrin pour nourrissons contre la fièvre et la douleur",
            "path": "/symptomes-chez-les-nourrissons-et-les-enfants"
        },
        {
            "number": "9",
            "image": "fevertaco-fr-3-re_0.png",
            "alt": "Produits Tylenol et Motrin pour nourrissons contre la fièvre et la douleur",
            "path": "/symptomes-chez-les-nourrissons-et-les-enfants/traiter-le-mal-de-dents-et-la-douleur-de-la-dentition"
        },
        {
            "number": "10",
            "image": "motrin-fr-ktd-landing-header.jpg",
            "alt": "MOTRIN® Nourrissons Douleur et fièvre, 8 heures, 30 ml",
            "path": "/symptomes-chez-les-nourrissons-et-les-enfants/faire-la-difference-page-d-accueil"
        },
        {
            "number": "11",
            "image": "motrin-childrens-wide-fr_0.jpg",
            "alt": "MOTRIN® Nourrissons Douleur et fièvre, 8 heures, Petits fruits, Sans colorant, 120 ml",
            "path": "/symptomes-chez-les-nourrissons-et-les-enfants"
        },
        {
            "number": "12",
            "image": "motrin_tout_fr.jpg",
            "alt": "Gélules Motrin, 60 u.",
            "path": "/nouvelles-et-promotions"
        },
        {
            "number": "13",
            "image": "fr_mot_platinum_40s_ff_f_s-1.jpg",
            "alt": "Motrin Platine Muscles et corps, 40 caplets",
            "path": "/produits/motrin/caplets-motrin-platine-muscles-et-corps"
        },
        {
            "number": "14",
            "image": "fevertaco-fr-3-re.png",
            "alt": "MOTRIN® Nourrissons Douleur et fièvre, 8 heures, Petits fruits, Sans colorant, 30 ml",
            "path": "/symptomes-chez-les-nourrissons-et-les-enfants/faire-la-difference-page-d-accueil"
        },
        {
            "number": "15",
            "image": "motrin-fr-ktd-infants-header_updated2_0.jpg",
            "alt": "Produits Tylenol et Motrin pour le soulagement de la fièvre et de la douleur chez les nourrissons",
            "path": "/symptomes-chez-les-nourrissons-et-les-enfants/faire-la-difference-page-d-accueil/faire-la-differen-0"
        },
        {
            "number": "16",
            "image": "fr_mot_platinum_40s_ff_f_s-1.jpg",
            "alt": "Motrin Platine Muscles et corps, 40 caplets",
            "path": "/produits"
        },
        {
            "number": "17",
            "image": "motrin-gels-fr-min.png",
            "alt": "Gélules Motrin, 30 u.",
            "path": "/produits/motrin/comprimes-motrin"
        },
        {
            "number": "18",
            "image": "motrin_carousel_mobile_fr.jpg",
            "alt": "Gélules Motrin, 60 u.",
            "path": "/nouvelles-et-promotions"
        },
        {
            "number": "19",
            "image": "3.3_headaches_header-min.jpg",
            "alt": "Une maman qui joue avec son enfant",
            "path": "/symptomes-chez-les-adultes/mal-de-tete"
        },
        {
            "number": "20",
            "image": "motrin_covid-19_banner.jpg",
            "alt": "Bannière de fond orange Motrin",
            "path": "/"
        },
        {
            "number": "21",
            "image": "motrin-diagnosingunderstandingbackpain-header.jpg",
            "alt": "Homme souffrant de douleurs au dos",
            "path": "/symptomes-chez-les-adultes/mal-de-dos/diagnostiquer-et-comprendre-le-mal-de-dos"
        },
        {
            "number": "22",
            "image": "table-dosin-08_b.jpg",
            "alt": "Icône de dosage par seringue",
            "path": "/innocuit%C3%A9-et-posologie/tableaux-posologiques-pour-nourrissons-et-pour-enfants "
        },
        {
            "number": "23",
            "image": "teething-header-image.png",
            "alt": "Jouet de dentition pour bébé",
            "path": "/symptomes-chez-les-nourrissons-et-les-enfants/traiter-le-mal-de-dents-et-la-douleur-de-la-dentition"
        },
        {
            "number": "24",
            "image": "product_lg_motrininfants.png",
            "alt": "MOTRIN® Nourrissons Douleur et fièvre, 8 heures, 30 ml",
            "path": "/produits/motrin/suspension-motrin-pour-enfants"
        },
        {
            "number": "25",
            "image": "peds_tylenol_motrin_website_update_fever_-_infants_en_final-2.png",
            "alt": "Comprendre la fièvre chez le nourrisson",
            "path": "/symptomes-chez-les-nourrissons-et-les-enfants/fievre/traitement-de-la-fievre-chez-les-nourrissons-et-les"
        },
        {
            "number": "26",
            "image": "4.2_fever_banner-1.jpg",
            "alt": "Bannière avec une petite fille prenant sa température",
            "path": "/symptomes-chez-les-nourrissons-et-les-enfants/fievre"
        },
        {
            "number": "27",
            "image": "motrin-menstrualpain-header.jpg",
            "alt": "Adolescente souffrant de douleurs menstruelles",
            "path": "/symptomes-chez-les-adultes/douleurs-menstruelles"
        },
        {
            "number": "28",
            "image": "teething-taco-1.png",
            "alt": "Bébé fait ses dents",
            "path": "/symptomes-chez-les-nourrissons-et-les-enfants/traiter-le-mal-de-dents-et-la-douleur-de-la-dentition"
        },
        {
            "number": "29",
            "image": "peds_tylenol_motrin_website_update_toothaches_en_final-1.png",
            "alt": "Petite fille souffrant de maux de dents",
            "path": "/symptomes-chez-les-nourrissons-et-les-enfants/4-astuces-pour-traiter-et-prevenir-le-mal-de-dents-chez-les-enfants"
        },
        {
            "number": "30",
            "image": "motrin-listingbackpain-header.jpg",
            "alt": "Bannière avec une femme qui s'étire sans souffrir de douleurs corporelles",
            "path": "/symptomes-chez-les-adultes/mal-de-dos"
        },
        {
            "number": "31",
            "image": "tylenol_motrin_website-1-min.png",
            "alt": "une maman qui donne le bain à son bébé",
            "path": "/symptomes-chez-les-nourrissons-et-les-enfants/fievre"
        },
        {
            "number": "32",
            "image": "table-dosin-09_c.jpg",
            "alt": "Icône de dosage Gobelet-doseur",
            "path": "/innocuit%C3%A9-et-posologie/tableaux-posologiques-pour-nourrissons-et-pour-enfants "
        },
        {
            "number": "33",
            "image": "taco-1-re.png",
            "alt": "Comment prendre la température de bébé",
            "path": "/symptomes-chez-les-nourrissons-et-les-enfants/faire-la-difference-page-d-accueil"
        },
        {
            "number": "34",
            "image": "motrin-listingbodypain-callout01.jpg",
            "alt": "Femme souffrant de douleurs corporelles",
            "path": "/symptomes-chez-les-adultes/douleurs-corporelles"
        },
        {
            "number": "35",
            "image": "4.0_children-and-infants_banner.jpg",
            "alt": "Bannière avec une petite fille souriante",
            "path": "/symptomes-chez-les-nourrissons-et-les-enfants"
        },
        {
            "number": "36",
            "image": "motrin-causesbackpain-header-min.jpg",
            "alt": "Homme souffrant de mal de dos au travail",
            "path": "/symptomes-chez-les-adultes/mal-de-dos/causes-de-la-douleur-au-haut-et-au-bas-du-dos"
        },
        {
            "number": "37",
            "image": "5.0_safetyanddosing_965x455_0.jpg",
            "alt": "Petite fille prenant sa température",
            "path": "/symptomes-chez-les-nourrissons-et-les-enfants/faire-la-difference-page-d-accueil"
        },
        {
            "number": "38",
            "image": "table-dosin-08_a.jpg",
            "alt": "Icône de dosage Seringue",
            "path": "/innocuit%C3%A9-et-posologie/tableaux-posologiques-pour-nourrissons-et-pour-enfants "
        },
        {
            "number": "39",
            "image": "motrin-teethingtoothaches-landing-fr.png",
            "alt": "Icône de mal de dents",
            "path": "/symptomes-chez-les-nourrissons-et-les-enfants/traiter-le-mal-de-dents-et-la-douleur-de-la-dentition"
        },
        {
            "number": "40",
            "image": "motrin-listingbackpain-callout01.jpg",
            "alt": "Femme souffrant d'un mal de dos",
            "path": "/symptomes-chez-les-adultes/mal-de-dos"
        },
        {
            "number": "41",
            "image": "motrin-listingbackpain-callout03_1_fr.jpg",
            "alt": "Femme souffrant de douleurs au dos",
            "path": "/symptomes-chez-les-adultes/mal-de-dos"
        },
        {
            "number": "42",
            "image": "motrin-muscleaches-header_resized.jpg",
            "alt": "Bannière d'une femme souffrant de douleurs corporelles",
            "path": "/symptomes-chez-les-adultes/douleurs-corporelles/douleurs-musculaires"
        },
        {
            "number": "43",
            "image": "motrin-listingbodypain-callout04.jpg",
            "alt": "Homme souffrant d'une douleur au genou",
            "path": "/symptomes-chez-les-adultes/douleurs-corporelles"
        },
        {
            "number": "44",
            "image": "table-dosin-09_b.jpg",
            "alt": "Icône de dosage Gobelet-doseur",
            "path": "/innocuit%C3%A9-et-posologie/tableaux-posologiques-pour-nourrissons-et-pour-enfants "
        },
        {
            "number": "45",
            "image": "motrin-headaches-header.jpg",
            "alt": "Femme souffrant de maux de tête",
            "path": "/symptomes-chez-les-adultes/maux-de-tete"
        },
        {
            "number": "46",
            "image": "motrin-managingpreventingbackpain-header.jpg",
            "alt": "Homme endormi et souffrant d'un mal de dos",
            "path": "/symptomes-chez-les-adultes/mal-de-dos/prise-en-charge-et-prevention-du-mal-de-dos"
        },
        {
            "number": "47",
            "image": "motrin-sprainsstrains-header.jpg",
            "alt": "Etirement de la jambe en raison d'une entorse musculaire",
            "path": "/symptomes-chez-les-adultes/douleurs-corporelles/entorses-et-foulures"
        },
        {
            "number": "48",
            "image": "motrin-listingbodypain-header.jpg",
            "alt": "Bannière d'une femme faisant du jogging sans souffrir de douleurs corporelles",
            "path": "/symptomes-chez-les-adultes/douleurs-corporelles"
        },
        {
            "number": "49",
            "image": "table-dosin-09_a.jpg",
            "alt": "Icône de dosage Gobelet-doseur",
            "path": "/innocuit%C3%A9-et-posologie/tableaux-posologiques-pour-nourrissons-et-pour-enfants "
        },
        {
            "number": "50",
            "image": "motrin-listingbackpain-callout02.jpg",
            "alt": "Femme souffrant d'un mal de dos",
            "path": "/symptomes-chez-les-adultes/mal-de-dos"
        },
        {
            "number": "51",
            "image": "motrin-kneepain-header.jpg",
            "alt": "Bannière d'un homme souffrant d'une douleur au genou",
            "path": "/symptomes-chez-les-adultes/douleurs-corporelles/douleur-au-genou"
        },
        {
            "number": "52",
            "image": "peds_tylenol_motrin_website_update_sprains_and_strains_en_final-2.png",
            "alt": "Père et fille jouant ensemble",
            "path": "/symptomes-chez-les-nourrissons-et-les-enfants/prise-en-charge-de-la-douleur-chez-les-enfants-entorses-et-foulures"
        },
        {
            "number": "53",
            "image": "motrin-listingbodypain-callout03-fr.jpg",
            "alt": "Femme souffrant d'une entorse musculaire",
            "path": "/symptomes-chez-les-adultes/douleurs-corporelles"
        },
        {
            "number": "54",
            "image": "motrin-jointpain-header.jpg",
            "alt": "Bannière avec une femme souffrant d'une entorse musculaire",
            "path": "/symptomes-chez-les-adultes/douleurs-corporelles/douleur-articulaire"
        },
        {
            "number": "55",
            "image": "peds_tylenol_motrin_website_update_teething_en_final.png",
            "alt": "Jouet de dentition pour bébé",
            "path": "/symptomes-chez-les-nourrissons-et-les-enfants/faire-face-la-douleur-de-la-dentition"
        },
        {
            "number": "56",
            "image": "5.0_safetyanddosing_965x455_2.jpg",
            "alt": "Petite fille prenant sa température",
            "path": "/symptomes-chez-les-nourrissons-et-les-enfants/fievre"
        },
        {
            "number": "57",
            "image": "motrin-knowthedifference-landing.png",
            "alt": "Icône Motrin",
            "path": "/symptomes-chez-les-nourrissons-et-les-enfants/faire-la-difference-page-d-accueil"
        },
        {
            "number": "58",
            "image": "4.2.2_for-children-2-11-years-old_banner.jpg",
            "alt": "Bannière d'un enfant jouant avec des jouets",
            "path": "/symptomes-chez-les-nourrissons-et-les-enfants/fievre/3-conseils-pour-soulager-la-fievre-chez-les"
        },
        {
            "number": "59",
            "image": "table-dosin-09_e.jpg",
            "alt": "Icône de dosage Gobelet-doseur",
            "path": "/innocuit%C3%A9-et-posologie/tableaux-posologiques-pour-nourrissons-et-pour-enfants "
        },
        {
            "number": "60",
            "image": "table-dosin-09_d.jpg",
            "alt": "Icône de dosage Gobelet-doseur",
            "path": "/innocuit%C3%A9-et-posologie/tableaux-posologiques-pour-nourrissons-et-pour-enfants "
        },
        {
            "number": "61",
            "image": "motrin-listingbackpain-callout04-fr.jpg",
            "alt": "Femme dormant paisiblement sans souffrir de douleurs corporelles",
            "path": "/symptomes-chez-les-adultes/mal-de-dos"
        },
        {
            "number": "62",
            "image": "product_lg_motrintablets_resized.png",
            "alt": "Comprimés Motrin, 45 u.",
            "path": "/produits/motrin/gelules-motrin"
        },
        {
            "number": "63",
            "image": "motrin-listingbodypain-callout02-fr.jpg",
            "alt": "Athlète s'étirant avant de s'entraîner",
            "path": "/symptomes-chez-les-adultes/douleurs-corporelles"
        },
        {
            "number": "64",
            "image": "3.1_joint_pain_image-min.jpg",
            "alt": "Femme faisant du yoga sans souffrir de douleurs articulaires",
            "path": "/symptomes-chez-les-adultes/douleurs-articulaires"
        }
    ]
}